README.md
package_info.json
setup.py
th2_grpc_conn/__init__.py
th2_grpc_conn/conn.proto
th2_grpc_conn/conn_pb2.py
th2_grpc_conn/conn_pb2_grpc.py
th2_grpc_conn/conn_service.py
th2_grpc_conn.egg-info/PKG-INFO
th2_grpc_conn.egg-info/SOURCES.txt
th2_grpc_conn.egg-info/dependency_links.txt
th2_grpc_conn.egg-info/requires.txt
th2_grpc_conn.egg-info/top_level.txt