Metadata-Version: 2.1
Name: th2-grpc-conn
Version: 0.0.1.dev983231218
Summary: th2_grpc_conn
Home-page: https://github.com/th2-net/th2-grpc-conn
Author: TH2-devs
Author-email: th2-devs@exactprosystems.com
License: Apache License 2.0
Platform: UNKNOWN
Requires-Python: >=3.7
